wordpiece_rs-0.1.0.dist-info/METADATA
wordpiece_rs-0.1.0.dist-info/WHEEL
wordpiece_rs-0.1.0.dist-info/licenses/LICENSE
wordpiece_rs/__init__.py
wordpiece_rs/wordpiece_rs.cpython-37m-x86_64-linux-gnu.so
wordpiece_rs-0.1.0.dist-info/RECORD
