Metadata-Version: 2.4
Name: wordpiece_rs
Version: 0.1.0
Classifier: Development Status :: 4 - Beta
Classifier: Intended Audience :: Developers
Classifier: Intended Audience :: Science/Research
Classifier: License :: OSI Approved :: MIT License
Classifier: Programming Language :: Python :: 3
Classifier: Programming Language :: Python :: 3.7
Classifier: Programming Language :: Python :: 3.8
Classifier: Programming Language :: Python :: 3.9
Classifier: Programming Language :: Python :: 3.10
Classifier: Programming Language :: Python :: 3.11
Classifier: Programming Language :: Python :: 3.12
Classifier: Programming Language :: Rust
Classifier: Topic :: Scientific/Engineering :: Artificial Intelligence
Classifier: Topic :: Text Processing :: Linguistic
License-File: LICENSE
Summary: A fast WordPiece tokenizer implementation in Rust with Python bindings
Keywords: nlp,tokenizer,wordpiece,rust,machine-learning
Author-email: OpenHands <openhands@all-hands.dev>
License: MIT
Requires-Python: >=3.7
Project-URL: Homepage, https://github.com/novastar53/wordpiece-rs
Project-URL: Repository, https://github.com/novastar53/wordpiece-rs
Project-URL: Documentation, https://github.com/novastar53/wordpiece-rs#readme
